jabl/__init__.py
jabl/jabl.py
jabl-0.0.1a2.dist-info/METADATA
jabl-0.0.1a2.dist-info/WHEEL
jabl-0.0.1a2.dist-info/LICENSE
jabl-0.0.1a2.dist-info/RECORD
